{
  "header-bar": {
    "container": {
      "width": {
        "value": "fill-available",
        "type": "sizing"
      },
      "height": {
        "value": "fit-content",
        "type": "sizing"
      },
      "row-gap": {
        "value": "{breakpoint.header-bar.container.row-gap}",
        "type": "spacing"
      }
    },
    "main-area": {
      "width": {
        "value": "fill-available",
        "type": "sizing"
      },
      "height": {
        "value": "fit-content",
        "type": "sizing"
      }
    },
    "secondary-area": {
      "width": {
        "value": "fill-available",
        "type": "sizing"
      },
      "height": {
        "value": "fit-content",
        "type": "sizing"
      }
    }
  }
}