{
  "indicator-tendency-icon": {
    "container": {
      "background": {
        "default": {
          "value": "{mode.alert.background.low.neutral.normal}",
          "type": "color"
        },
        "critical": {
          "value": "{mode.alert.background.low.danger.normal}",
          "type": "color"
        },
        "none": {
          "value": "{mode.surface.none}",
          "type": "color"
        }
      },
      "border-radius": {
        "default": {
          "value": "{generation.shape.corner.small}",
          "type": "borderRadius"
        }
      },
      "padding-top": {
        "default": {
          "small": {
            "value": "6px",
            "type": "spacing"
          },
          "medium": {
            "value": "6px",
            "type": "spacing"
          }
        },
        "none": {
          "small": {
            "value": "6px",
            "type": "spacing"
          },
          "medium": {
            "value": "6px",
            "type": "spacing"
          }
        }
      },
      "padding-bottom": {
        "default": {
          "small": {
            "value": "6px",
            "type": "spacing"
          },
          "medium": {
            "value": "6px",
            "type": "spacing"
          }
        },
        "none": {
          "small": {
            "value": "6px",
            "type": "spacing"
          },
          "medium": {
            "value": "6px",
            "type": "spacing"
          }
        }
      },
      "padding-right": {
        "default": {
          "small": {
            "value": "{foundation.space.2}",
            "type": "spacing"
          },
          "medium": {
            "value": "{foundation.space.2}",
            "type": "spacing"
          }
        },
        "none": {
          "small": {
            "value": "{foundation.space.none}",
            "type": "spacing"
          },
          "medium": {
            "value": "{foundation.space.none}",
            "type": "spacing"
          }
        }
      },
      "padding-left": {
        "default": {
          "small": {
            "value": "{foundation.space.2}",
            "type": "spacing"
          },
          "medium": {
            "value": "{foundation.space.2}",
            "type": "spacing"
          }
        },
        "none": {
          "small": {
            "value": "{foundation.space.none}",
            "type": "spacing"
          },
          "medium": {
            "value": "{foundation.space.none}",
            "type": "spacing"
          }
        }
      },
      "outline-offset": {
        "focus-visible": {
          "value": "{foundation.space.offset.xxsmall}",
          "type": "spacing"
        }
      },
      "outline": {
        "focus-visible": {
          "value": "{mode.outline.focus-visible}",
          "type": "border"
        }
      }
    },
    "icon": {
      "color": {
        "neutral": {
          "value": "{mode.alert.background.high.neutral.normal}",
          "type": "color"
        },
        "danger": {
          "value": "{mode.alert.background.high.danger.normal}",
          "type": "color"
        },
        "warning": {
          "value": "{mode.alert.background.high.warning.normal}",
          "type": "color"
        },
        "caution": {
          "value": "{mode.alert.background.high.caution.normal}",
          "type": "color"
        },
        "safety": {
          "value": "{mode.alert.background.high.safety.normal}",
          "type": "color"
        },
        "notice": {
          "value": "{mode.alert.background.high.information.normal}",
          "type": "color"
        }
      },
      "width": {
        "small": {
          "value": "{generation.dimension.4}",
          "type": "sizing"
        },
        "medium": {
          "value": "{generation.dimension.6}",
          "type": "sizing"
        }
      },
      "height": {
        "small": {
          "value": "{generation.dimension.4}",
          "type": "sizing"
        },
        "medium": {
          "value": "{generation.dimension.6}",
          "type": "sizing"
        }
      },
      "flat": {
        "value": "EmrIconIndeterminateStateSvg",
        "type": "asset"
      },
      "up": {
        "value": "DlsIconDateArrowUpSvg",
        "type": "asset"
      },
      "down": {
        "value": "DlsIconDateArrowDownSvg",
        "type": "asset"
      }
    }
  }
}